sourcestack/__init__.py
sourcestack/client.py
sourcestack/exceptions.py
sourcestack/jobs.py
sourcestack/resource.py
sourcestack/search.py
sourcestack-0.1.1.dist-info/LICENSE
sourcestack-0.1.1.dist-info/METADATA
sourcestack-0.1.1.dist-info/WHEEL
sourcestack-0.1.1.dist-info/top_level.txt
sourcestack-0.1.1.dist-info/RECORD
