Metadata-Version: 2.2
Name: sourcestack
Version: 0.1.1
Summary: A python package for using the https://sourcestack.co/ API.
Author-email: Kevin Sylvestre <kevin@ksylvest.com>, Dean Singh <dean.singh@gmail.com>
License: MIT
Project-URL: Homepage, https://github.com/workflowing/sourcestack
Keywords: sourcestack
Classifier: Development Status :: 3 - Alpha
Classifier: Intended Audience :: Developers
Classifier: License :: OSI Approved :: MIT License
Classifier: Programming Language :: Python :: 3
License-File: LICENSE
Requires-Dist: requests
Provides-Extra: dev
Requires-Dist: pytest>=6.0; extra == "dev"
Requires-Dist: pytest-cov>=2.0; extra == "dev"
Requires-Dist: pytest-mock>=3.10.0; extra == "dev"
Requires-Dist: responses>=0.23.0; extra == "dev"
Requires-Dist: python-dotenv>=1.0.0; extra == "dev"
Requires-Dist: black>=21.0; extra == "dev"
Requires-Dist: isort>=5.0; extra == "dev"
Requires-Dist: mypy>=0.900; extra == "dev"
Requires-Dist: flake8>=3.9; extra == "dev"
Requires-Dist: twine; extra == "dev"
